preprocess/__init__.py
preprocess/element.py
preprocess/html.py
preprocess/pdf.py
preprocess_docs-0.0.6.dist-info/LICENSE
preprocess_docs-0.0.6.dist-info/METADATA
preprocess_docs-0.0.6.dist-info/WHEEL
preprocess_docs-0.0.6.dist-info/top_level.txt
preprocess_docs-0.0.6.dist-info/RECORD
