Metadata-Version: 2.1
Name: preprocess-docs
Version: 0.0.6
Summary: An open source document preprocessor for AI.
Home-page: https://github.com/eddyjin1/preprocess
Author: Eddy Jin
Keywords: preprocess extract transform load parse documents html pdf images tables
Classifier: Programming Language :: Python :: 3
Classifier: License :: OSI Approved :: MIT License
Classifier: Operating System :: OS Independent
Classifier: Development Status :: 1 - Planning
Classifier: Intended Audience :: Developers
Classifier: Intended Audience :: Education
Classifier: Intended Audience :: Science/Research
Classifier: Topic :: Scientific/Engineering :: Artificial Intelligence
Requires-Python: >=3.6
License-File: LICENSE
Requires-Dist: beautifulsoup4
Requires-Dist: pdfminer.six
